docume_llm/__init__.py
docume_llm/main.py
docume_llm/src/__init__.py
docume_llm/src/chains/__init__.py
docume_llm/src/chains/chain.py
docume_llm/src/chains/loader/__init__.py
docume_llm/src/chains/loader/custom_json_loader.py
docume_llm/src/grouping/__init__.py
docume_llm/src/grouping/grouping_factory.py
docume_llm/src/jira/__init__.py
docume_llm/src/jira/grouping.py
docume_llm/src/jira/preprocess_jira.py
docume_llm/src/preprocess/__init__.py
docume_llm/src/preprocess/preprocess_factory.py
docume_llm/src/service/__init__.py
docume_llm/src/service/service.py
docume_llm/src/utils/__init__.py
docume_llm/src/utils/config.py
docume_llm/src/utils/data.py
docume_llm/src/utils/llm_model.py
docume_llm/src/validators/__init__.py
docume_llm/src/validators/doc_validator.py
docume_llm-0.1.0.dist-info/METADATA
docume_llm-0.1.0.dist-info/WHEEL
docume_llm-0.1.0.dist-info/entry_points.txt
docume_llm-0.1.0.dist-info/top_level.txt
docume_llm-0.1.0.dist-info/RECORD
